odbcinst/__init__.py
odbcinst/_base.py
odbcinst-1.0.1.dist-info/LICENSE
odbcinst-1.0.1.dist-info/METADATA
odbcinst-1.0.1.dist-info/WHEEL
odbcinst-1.0.1.dist-info/top_level.txt
odbcinst-1.0.1.dist-info/RECORD
