Metadata-Version: 2.1
Name: odbcinst
Version: 1.0.1
Summary: return output from unixODBC `odbcinst` command
Home-page: https://github.com/gordthompson/odbcinst
Author: Gord Thompson
Author-email: gord@gordthompson.com
License: MIT
Keywords: unixODBC
Platform: UNKNOWN
Classifier: Development Status :: 5 - Production/Stable
Classifier: Intended Audience :: Developers
Classifier: Programming Language :: Python :: 3
Classifier: License :: OSI Approved :: MIT License
Classifier: Operating System :: Unix
